MANIFEST.in
setup.py
bin/cocoag
cocoag/__init__.py
cocoag.egg-info/PKG-INFO
cocoag.egg-info/SOURCES.txt
cocoag.egg-info/dependency_links.txt
cocoag.egg-info/requires.txt
cocoag.egg-info/top_level.txt
cocoag/configuration/__init__.py
cocoag/configuration/config.py
cocoag/configuration/default_cocoag.cfg
cocoag/configuration/__pycache__/__init__.cpython-36.pyc
cocoag/configuration/__pycache__/config.cpython-36.pyc
cocoag/generator/__init__.py
cocoag/generator/coverage_generator.py
cocoag/generator/test/conftest.py
cocoag/generator/test/test_coverage_generator.py
cocoag/generator/test/utils/readme_writer/conftest.py
cocoag/generator/test/utils/readme_writer/test_readme_writer.py
cocoag/generator/utils/__init__.py
cocoag/generator/utils/readme_writer/__init__.py
cocoag/generator/utils/readme_writer/writer.py
cocoag/s3/__init__.py
cocoag/s3/s3_client.py
cocoag/s3/test/test_s3_client.py