Metadata-Version: 1.1
Name: cocoag
Version: 1.1.2b0
Summary: Python utility to generate code coverage badges and append them to README's
Home-page: http://cocoag.org
Author: David Cyze
Author-email: mrcyze@gmail.com
License: UNKNOWN
Download-URL: https://github.com/PrettyCities/cocoag
Keywords: automation,code coverage,testing
Platform: UNKNOWN
Classifier: Programming Language :: Python :: 3
Classifier: Development Status :: 4 - Beta
Classifier: Environment :: MacOS X
Classifier: Intended Audience :: Developers
Classifier: License :: OSI Approved :: MIT License
Classifier: Operating System :: MacOS :: MacOS X
Classifier: Topic :: Documentation
Classifier: Topic :: Software Development :: Build Tools
Classifier: Topic :: Software Development :: Testing
Classifier: Topic :: Software Development :: Quality Assurance
Classifier: Topic :: Utilities
